{
  "DATE": "2026-04-22",
  "generated_at": "2026-04-22T07:55:52.953367+00:00",
  "games": [
    {
      "DATE": "2026-04-22",
      "GAME_ID": "MIA_STL",
      "home_team": "MIA",
      "away_team": "STL",
      "momentum": {
        "home_team": {
          "record_L5": "2-3",
          "record_L10": "3-7",
          "streak": "L1",
          "close_game_L10": "4-1"
        },
        "away_team": {
          "record_L5": "4-1",
          "record_L10": "6-4",
          "streak": "W1",
          "close_game_L10": "5-0"
        }
      },
      "fatigue": {
        "home_team": {
          "played_yesterday": true,
          "yesterday_location": "HOME",
          "travel_distance_km": 0,
          "timezone_change": 0,
          "games_without_rest": 5,
          "doubleheader": "NONE",
          "games_L7": 6
        },
        "away_team": {
          "played_yesterday": true,
          "yesterday_location": "AWAY",
          "travel_distance_km": 0,
          "timezone_change": 0,
          "games_without_rest": 5,
          "doubleheader": "NONE",
          "games_L7": 6
        }
      },
      "motivation": {
        "home_team": {
          "division_rank": 2,
          "games_behind_leader": 5.0,
          "wildcard_gb": 3.5
        },
        "away_team": {
          "division_rank": 3,
          "games_behind_leader": 1.5,
          "wildcard_gb": 0.0
        },
        "series_position": "3/3",
        "series_record": "1-1",
        "sweep_risk": false,
        "sweep_chance": false,
        "rivalry_tag": null
      },
      "schedule_context": {
        "days_to_allstar": 84,
        "days_to_deadline": 100,
        "expanded_roster": false
      }
    },
    {
      "DATE": "2026-04-22",
      "GAME_ID": "CLE_HOU",
      "home_team": "CLE",
      "away_team": "HOU",
      "momentum": {
        "home_team": {
          "record_L5": "3-2",
          "record_L10": "5-5",
          "streak": "W1",
          "close_game_L10": "3-2"
        },
        "away_team": {
          "record_L5": "1-4",
          "record_L10": "3-7",
          "streak": "L1",
          "close_game_L10": "1-2"
        }
      },
      "fatigue": {
        "home_team": {
          "played_yesterday": true,
          "yesterday_location": "HOME",
          "travel_distance_km": 0,
          "timezone_change": 0,
          "games_without_rest": 12,
          "doubleheader": "NONE",
          "games_L7": 7
        },
        "away_team": {
          "played_yesterday": true,
          "yesterday_location": "AWAY",
          "travel_distance_km": 0,
          "timezone_change": 0,
          "games_without_rest": 12,
          "doubleheader": "NONE",
          "games_L7": 7
        }
      },
      "motivation": {
        "home_team": {
          "division_rank": 1,
          "games_behind_leader": 0.0,
          "wildcard_gb": 0.0
        },
        "away_team": {
          "division_rank": 5,
          "games_behind_leader": 4.5,
          "wildcard_gb": 4.0
        },
        "series_position": "3/3",
        "series_record": "1-1",
        "sweep_risk": false,
        "sweep_chance": false,
        "rivalry_tag": null
      },
      "schedule_context": {
        "days_to_allstar": 84,
        "days_to_deadline": 100,
        "expanded_roster": false
      }
    },
    {
      "DATE": "2026-04-22",
      "GAME_ID": "TB_CIN",
      "home_team": "TB",
      "away_team": "CIN",
      "momentum": {
        "home_team": {
          "record_L5": "1-4",
          "record_L10": "6-4",
          "streak": "L3",
          "close_game_L10": "4-1"
        },
        "away_team": {
          "record_L5": "5-0",
          "record_L10": "8-2",
          "streak": "W5",
          "close_game_L10": "6-0"
        }
      },
      "fatigue": {
        "home_team": {
          "played_yesterday": true,
          "yesterday_location": "HOME",
          "travel_distance_km": 0,
          "timezone_change": 0,
          "games_without_rest": 8,
          "doubleheader": "NONE",
          "games_L7": 7
        },
        "away_team": {
          "played_yesterday": true,
          "yesterday_location": "AWAY",
          "travel_distance_km": 0,
          "timezone_change": 0,
          "games_without_rest": 8,
          "doubleheader": "NONE",
          "games_L7": 7
        }
      },
      "motivation": {
        "home_team": {
          "division_rank": 2,
          "games_behind_leader": 2.0,
          "wildcard_gb": 0.0
        },
        "away_team": {
          "division_rank": 1,
          "games_behind_leader": 0.0,
          "wildcard_gb": 0.0
        },
        "series_position": "3/3",
        "series_record": "0-2",
        "sweep_risk": true,
        "sweep_chance": true,
        "rivalry_tag": null
      },
      "schedule_context": {
        "days_to_allstar": 84,
        "days_to_deadline": 100,
        "expanded_roster": false
      }
    },
    {
      "DATE": "2026-04-22",
      "GAME_ID": "KC_BAL",
      "home_team": "KC",
      "away_team": "BAL",
      "momentum": {
        "home_team": {
          "record_L5": "1-4",
          "record_L10": "2-8",
          "streak": "W1",
          "close_game_L10": "1-5"
        },
        "away_team": {
          "record_L5": "2-3",
          "record_L10": "4-6",
          "streak": "L1",
          "close_game_L10": "2-4"
        }
      },
      "fatigue": {
        "home_team": {
          "played_yesterday": true,
          "yesterday_location": "HOME",
          "travel_distance_km": 0,
          "timezone_change": 0,
          "games_without_rest": 8,
          "doubleheader": "NONE",
          "games_L7": 7
        },
        "away_team": {
          "played_yesterday": true,
          "yesterday_location": "AWAY",
          "travel_distance_km": 0,
          "timezone_change": 0,
          "games_without_rest": 12,
          "doubleheader": "NONE",
          "games_L7": 7
        }
      },
      "motivation": {
        "home_team": {
          "division_rank": 5,
          "games_behind_leader": 5.5,
          "wildcard_gb": 4.5
        },
        "away_team": {
          "division_rank": 3,
          "games_behind_leader": 3.5,
          "wildcard_gb": 1.5
        },
        "series_position": "3/3",
        "series_record": "1-1",
        "sweep_risk": false,
        "sweep_chance": false,
        "rivalry_tag": null
      },
      "schedule_context": {
        "days_to_allstar": 84,
        "days_to_deadline": 100,
        "expanded_roster": false
      }
    },
    {
      "DATE": "2026-04-22",
      "GAME_ID": "LAA_TOR",
      "home_team": "LAA",
      "away_team": "TOR",
      "momentum": {
        "home_team": {
          "record_L5": "1-4",
          "record_L10": "4-6",
          "streak": "L4",
          "close_game_L10": "2-3"
        },
        "away_team": {
          "record_L5": "3-2",
          "record_L10": "4-6",
          "streak": "W3",
          "close_game_L10": "3-4"
        }
      },
      "fatigue": {
        "home_team": {
          "played_yesterday": true,
          "yesterday_location": "HOME",
          "travel_distance_km": 0,
          "timezone_change": 0,
          "games_without_rest": 12,
          "doubleheader": "NONE",
          "games_L7": 7
        },
        "away_team": {
          "played_yesterday": true,
          "yesterday_location": "AWAY",
          "travel_distance_km": 0,
          "timezone_change": 0,
          "games_without_rest": 8,
          "doubleheader": "NONE",
          "games_L7": 7
        }
      },
      "motivation": {
        "home_team": {
          "division_rank": 3,
          "games_behind_leader": 2.5,
          "wildcard_gb": 2.0
        },
        "away_team": {
          "division_rank": 4,
          "games_behind_leader": 4.0,
          "wildcard_gb": 2.0
        },
        "series_position": "3/3",
        "series_record": "0-2",
        "sweep_risk": true,
        "sweep_chance": true,
        "rivalry_tag": null
      },
      "schedule_context": {
        "days_to_allstar": 84,
        "days_to_deadline": 100,
        "expanded_roster": false
      }
    },
    {
      "DATE": "2026-04-22",
      "GAME_ID": "SEA_OAK",
      "home_team": "SEA",
      "away_team": "OAK",
      "momentum": {
        "home_team": {
          "record_L5": "2-3",
          "record_L10": "4-6",
          "streak": "L2",
          "close_game_L10": "2-6"
        },
        "away_team": {
          "record_L5": "3-2",
          "record_L10": "6-4",
          "streak": "W2",
          "close_game_L10": "6-2"
        }
      },
      "fatigue": {
        "home_team": {
          "played_yesterday": true,
          "yesterday_location": "HOME",
          "travel_distance_km": 0,
          "timezone_change": 0,
          "games_without_rest": 12,
          "doubleheader": "NONE",
          "games_L7": 7
        },
        "away_team": {
          "played_yesterday": true,
          "yesterday_location": "AWAY",
          "travel_distance_km": 0,
          "timezone_change": 0,
          "games_without_rest": 15,
          "doubleheader": "NONE",
          "games_L7": 7
        }
      },
      "motivation": {
        "home_team": {
          "division_rank": 4,
          "games_behind_leader": 3.5,
          "wildcard_gb": 3.0
        },
        "away_team": {
          "division_rank": 1,
          "games_behind_leader": 0.0,
          "wildcard_gb": 0.0
        },
        "series_position": "3/3",
        "series_record": "0-2",
        "sweep_risk": true,
        "sweep_chance": true,
        "rivalry_tag": null
      },
      "schedule_context": {
        "days_to_allstar": 84,
        "days_to_deadline": 100,
        "expanded_roster": false
      }
    },
    {
      "DATE": "2026-04-22",
      "GAME_ID": "DET_MIL",
      "home_team": "DET",
      "away_team": "MIL",
      "momentum": {
        "home_team": {
          "record_L5": "2-3",
          "record_L10": "7-3",
          "streak": "L2",
          "close_game_L10": "3-2"
        },
        "away_team": {
          "record_L5": "4-1",
          "record_L10": "5-5",
          "streak": "W1",
          "close_game_L10": "2-2"
        }
      },
      "fatigue": {
        "home_team": {
          "played_yesterday": true,
          "yesterday_location": "HOME",
          "travel_distance_km": 0,
          "timezone_change": 0,
          "games_without_rest": 8,
          "doubleheader": "NONE",
          "games_L7": 7
        },
        "away_team": {
          "played_yesterday": true,
          "yesterday_location": "AWAY",
          "travel_distance_km": 0,
          "timezone_change": 0,
          "games_without_rest": 1,
          "doubleheader": "NONE",
          "games_L7": 6
        }
      },
      "motivation": {
        "home_team": {
          "division_rank": 3,
          "games_behind_leader": 1.5,
          "wildcard_gb": 0.5
        },
        "away_team": {
          "division_rank": 4,
          "games_behind_leader": 2.0,
          "wildcard_gb": 0.5
        },
        "series_position": "2/3",
        "series_record": "0-1",
        "sweep_risk": false,
        "sweep_chance": false,
        "rivalry_tag": null
      },
      "schedule_context": {
        "days_to_allstar": 84,
        "days_to_deadline": 100,
        "expanded_roster": false
      }
    },
    {
      "DATE": "2026-04-22",
      "GAME_ID": "WSH_ATL",
      "home_team": "WSH",
      "away_team": "ATL",
      "momentum": {
        "home_team": {
          "record_L5": "2-3",
          "record_L10": "5-5",
          "streak": "W1",
          "close_game_L10": "2-4"
        },
        "away_team": {
          "record_L5": "4-1",
          "record_L10": "7-3",
          "streak": "L1",
          "close_game_L10": "1-2"
        }
      },
      "fatigue": {
        "home_team": {
          "played_yesterday": true,
          "yesterday_location": "HOME",
          "travel_distance_km": 0,
          "timezone_change": 0,
          "games_without_rest": 12,
          "doubleheader": "NONE",
          "games_L7": 7
        },
        "away_team": {
          "played_yesterday": true,
          "yesterday_location": "AWAY",
          "travel_distance_km": 0,
          "timezone_change": 0,
          "games_without_rest": 5,
          "doubleheader": "NONE",
          "games_L7": 6
        }
      },
      "motivation": {
        "home_team": {
          "division_rank": 3,
          "games_behind_leader": 5.0,
          "wildcard_gb": 3.5
        },
        "away_team": {
          "division_rank": 1,
          "games_behind_leader": 0.0,
          "wildcard_gb": 0.0
        },
        "series_position": "3/3",
        "series_record": "1-1",
        "sweep_risk": false,
        "sweep_chance": false,
        "rivalry_tag": null
      },
      "schedule_context": {
        "days_to_allstar": 84,
        "days_to_deadline": 100,
        "expanded_roster": false
      }
    },
    {
      "DATE": "2026-04-22",
      "GAME_ID": "BOS_NYY",
      "home_team": "BOS",
      "away_team": "NYY",
      "momentum": {
        "home_team": {
          "record_L5": "2-3",
          "record_L10": "5-5",
          "streak": "L1",
          "close_game_L10": "2-4"
        },
        "away_team": {
          "record_L5": "4-1",
          "record_L10": "6-4",
          "streak": "W4",
          "close_game_L10": "2-6"
        }
      },
      "fatigue": {
        "home_team": {
          "played_yesterday": true,
          "yesterday_location": "HOME",
          "travel_distance_km": 0,
          "timezone_change": 0,
          "games_without_rest": 5,
          "doubleheader": "NONE",
          "games_L7": 6
        },
        "away_team": {
          "played_yesterday": true,
          "yesterday_location": "AWAY",
          "travel_distance_km": 0,
          "timezone_change": 0,
          "games_without_rest": 1,
          "doubleheader": "NONE",
          "games_L7": 6
        }
      },
      "motivation": {
        "home_team": {
          "division_rank": 5,
          "games_behind_leader": 5.0,
          "wildcard_gb": 3.0
        },
        "away_team": {
          "division_rank": 1,
          "games_behind_leader": 0.0,
          "wildcard_gb": 0.0
        },
        "series_position": "2/3",
        "series_record": "0-1",
        "sweep_risk": false,
        "sweep_chance": false,
        "rivalry_tag": "NYY_BOS"
      },
      "schedule_context": {
        "days_to_allstar": 84,
        "days_to_deadline": 100,
        "expanded_roster": false
      }
    },
    {
      "DATE": "2026-04-22",
      "GAME_ID": "NYM_MIN",
      "home_team": "NYM",
      "away_team": "MIN",
      "momentum": {
        "home_team": {
          "record_L5": "0-5",
          "record_L10": "0-10",
          "streak": "L12",
          "close_game_L10": "1-5"
        },
        "away_team": {
          "record_L5": "1-4",
          "record_L10": "5-5",
          "streak": "W1",
          "close_game_L10": "0-3"
        }
      },
      "fatigue": {
        "home_team": {
          "played_yesterday": true,
          "yesterday_location": "HOME",
          "travel_distance_km": 0,
          "timezone_change": 0,
          "games_without_rest": 1,
          "doubleheader": "NONE",
          "games_L7": 5
        },
        "away_team": {
          "played_yesterday": true,
          "yesterday_location": "AWAY",
          "travel_distance_km": 0,
          "timezone_change": 0,
          "games_without_rest": 1,
          "doubleheader": "NONE",
          "games_L7": 5
        }
      },
      "motivation": {
        "home_team": {
          "division_rank": 5,
          "games_behind_leader": 8.5,
          "wildcard_gb": 7.0
        },
        "away_team": {
          "division_rank": 2,
          "games_behind_leader": 1.0,
          "wildcard_gb": 0.0
        },
        "series_position": "2/3",
        "series_record": "0-1",
        "sweep_risk": false,
        "sweep_chance": false,
        "rivalry_tag": null
      },
      "schedule_context": {
        "days_to_allstar": 84,
        "days_to_deadline": 100,
        "expanded_roster": false
      }
    },
    {
      "DATE": "2026-04-22",
      "GAME_ID": "CHC_PHI",
      "home_team": "CHC",
      "away_team": "PHI",
      "momentum": {
        "home_team": {
          "record_L5": "5-0",
          "record_L10": "8-2",
          "streak": "W7",
          "close_game_L10": "3-2"
        },
        "away_team": {
          "record_L5": "0-5",
          "record_L10": "2-8",
          "streak": "L7",
          "close_game_L10": "4-3"
        }
      },
      "fatigue": {
        "home_team": {
          "played_yesterday": true,
          "yesterday_location": "HOME",
          "travel_distance_km": 0,
          "timezone_change": 0,
          "games_without_rest": 5,
          "doubleheader": "NONE",
          "games_L7": 6
        },
        "away_team": {
          "played_yesterday": true,
          "yesterday_location": "AWAY",
          "travel_distance_km": 0,
          "timezone_change": 0,
          "games_without_rest": 5,
          "doubleheader": "NONE",
          "games_L7": 6
        }
      },
      "motivation": {
        "home_team": {
          "division_rank": 2,
          "games_behind_leader": 1.5,
          "wildcard_gb": 0.0
        },
        "away_team": {
          "division_rank": 4,
          "games_behind_leader": 7.5,
          "wildcard_gb": 6.0
        },
        "series_position": "3/3",
        "series_record": "2-0",
        "sweep_risk": true,
        "sweep_chance": true,
        "rivalry_tag": null
      },
      "schedule_context": {
        "days_to_allstar": 84,
        "days_to_deadline": 100,
        "expanded_roster": false
      }
    },
    {
      "DATE": "2026-04-22",
      "GAME_ID": "TEX_PIT",
      "home_team": "TEX",
      "away_team": "PIT",
      "momentum": {
        "home_team": {
          "record_L5": "3-2",
          "record_L10": "5-5",
          "streak": "W1",
          "close_game_L10": "3-4"
        },
        "away_team": {
          "record_L5": "2-3",
          "record_L10": "5-5",
          "streak": "L1",
          "close_game_L10": "4-4"
        }
      },
      "fatigue": {
        "home_team": {
          "played_yesterday": true,
          "yesterday_location": "HOME",
          "travel_distance_km": 0,
          "timezone_change": 0,
          "games_without_rest": 1,
          "doubleheader": "NONE",
          "games_L7": 6
        },
        "away_team": {
          "played_yesterday": true,
          "yesterday_location": "AWAY",
          "travel_distance_km": 0,
          "timezone_change": 0,
          "games_without_rest": 1,
          "doubleheader": "NONE",
          "games_L7": 6
        }
      },
      "motivation": {
        "home_team": {
          "division_rank": 2,
          "games_behind_leader": 0.5,
          "wildcard_gb": 0.0
        },
        "away_team": {
          "division_rank": 5,
          "games_behind_leader": 2.5,
          "wildcard_gb": 1.0
        },
        "series_position": "2/3",
        "series_record": "1-0",
        "sweep_risk": false,
        "sweep_chance": false,
        "rivalry_tag": null
      },
      "schedule_context": {
        "days_to_allstar": 84,
        "days_to_deadline": 100,
        "expanded_roster": false
      }
    },
    {
      "DATE": "2026-04-22",
      "GAME_ID": "COL_SD",
      "home_team": "COL",
      "away_team": "SD",
      "momentum": {
        "home_team": {
          "record_L5": "2-3",
          "record_L10": "3-7",
          "streak": "L2",
          "close_game_L10": "3-6"
        },
        "away_team": {
          "record_L5": "4-1",
          "record_L10": "9-1",
          "streak": "W3",
          "close_game_L10": "4-1"
        }
      },
      "fatigue": {
        "home_team": {
          "played_yesterday": true,
          "yesterday_location": "HOME",
          "travel_distance_km": 0,
          "timezone_change": 0,
          "games_without_rest": 8,
          "doubleheader": "NONE",
          "games_L7": 7
        },
        "away_team": {
          "played_yesterday": true,
          "yesterday_location": "AWAY",
          "travel_distance_km": 0,
          "timezone_change": 0,
          "games_without_rest": 1,
          "doubleheader": "NONE",
          "games_L7": 6
        }
      },
      "motivation": {
        "home_team": {
          "division_rank": 5,
          "games_behind_leader": 7.5,
          "wildcard_gb": 5.5
        },
        "away_team": {
          "division_rank": 1,
          "games_behind_leader": 0.0,
          "wildcard_gb": 0.0
        },
        "series_position": "2/3",
        "series_record": "0-1",
        "sweep_risk": false,
        "sweep_chance": false,
        "rivalry_tag": null
      },
      "schedule_context": {
        "days_to_allstar": 84,
        "days_to_deadline": 100,
        "expanded_roster": false
      }
    },
    {
      "DATE": "2026-04-22",
      "GAME_ID": "ARI_CWS",
      "home_team": "ARI",
      "away_team": "CWS",
      "momentum": {
        "home_team": {
          "record_L5": "3-2",
          "record_L10": "6-4",
          "streak": "L2",
          "close_game_L10": "6-4"
        },
        "away_team": {
          "record_L5": "3-2",
          "record_L10": "4-6",
          "streak": "W2",
          "close_game_L10": "2-2"
        }
      },
      "fatigue": {
        "home_team": {
          "played_yesterday": true,
          "yesterday_location": "HOME",
          "travel_distance_km": 0,
          "timezone_change": 0,
          "games_without_rest": 1,
          "doubleheader": "NONE",
          "games_L7": 5
        },
        "away_team": {
          "played_yesterday": true,
          "yesterday_location": "AWAY",
          "travel_distance_km": 0,
          "timezone_change": 0,
          "games_without_rest": 1,
          "doubleheader": "NONE",
          "games_L7": 6
        }
      },
      "motivation": {
        "home_team": {
          "division_rank": 3,
          "games_behind_leader": 3.0,
          "wildcard_gb": 1.0
        },
        "away_team": {
          "division_rank": 4,
          "games_behind_leader": 4.0,
          "wildcard_gb": 3.0
        },
        "series_position": "2/3",
        "series_record": "0-1",
        "sweep_risk": false,
        "sweep_chance": false,
        "rivalry_tag": null
      },
      "schedule_context": {
        "days_to_allstar": 84,
        "days_to_deadline": 100,
        "expanded_roster": false
      }
    },
    {
      "DATE": "2026-04-22",
      "GAME_ID": "SF_LAD",
      "home_team": "SF",
      "away_team": "LAD",
      "momentum": {
        "home_team": {
          "record_L5": "4-1",
          "record_L10": "5-5",
          "streak": "W1",
          "close_game_L10": "2-1"
        },
        "away_team": {
          "record_L5": "2-3",
          "record_L10": "6-4",
          "streak": "L1",
          "close_game_L10": "4-2"
        }
      },
      "fatigue": {
        "home_team": {
          "played_yesterday": true,
          "yesterday_location": "HOME",
          "travel_distance_km": 0,
          "timezone_change": 0,
          "games_without_rest": 1,
          "doubleheader": "NONE",
          "games_L7": 6
        },
        "away_team": {
          "played_yesterday": true,
          "yesterday_location": "AWAY",
          "travel_distance_km": 0,
          "timezone_change": 0,
          "games_without_rest": 5,
          "doubleheader": "NONE",
          "games_L7": 6
        }
      },
      "motivation": {
        "home_team": {
          "division_rank": 4,
          "games_behind_leader": 6.0,
          "wildcard_gb": 4.0
        },
        "away_team": {
          "division_rank": 2,
          "games_behind_leader": 0.0,
          "wildcard_gb": 2.0
        },
        "series_position": "2/3",
        "series_record": "1-0",
        "sweep_risk": false,
        "sweep_chance": false,
        "rivalry_tag": "LAD_SF"
      },
      "schedule_context": {
        "days_to_allstar": 84,
        "days_to_deadline": 100,
        "expanded_roster": false
      }
    }
  ]
}